README.md
flask_ruko.py
setup.py
Flask_Ruko.egg-info/PKG-INFO
Flask_Ruko.egg-info/SOURCES.txt
Flask_Ruko.egg-info/dependency_links.txt
Flask_Ruko.egg-info/requires.txt
Flask_Ruko.egg-info/top_level.txt