Metadata-Version: 1.1
Name: Flask-Ruko
Version: 1.0.0
Summary: A Flask extension to connect to a Ruko database
Home-page: https://github.com/rukodb/flask-ruko
Author: Matthew Scholefield
Author-email: matthew331199@gmail.com
License: MIT
Keywords: ruko database in-memory
Platform: UNKNOWN
Classifier: Environment :: Web Environment
Classifier: Intended Audience :: Developers
Classifier: Operating System :: OS Independent
Classifier: License :: OSI Approved :: MIT License
Classifier: Topic :: Database :: Database Engines/Servers
Classifier: Topic :: Internet :: WWW/HTTP :: Dynamic Content
Classifier: Topic :: Software Development :: Libraries :: Python Modules
Classifier: Programming Language :: Python :: 3 :: Only
Classifier: Programming Language :: Python :: 3.4
Classifier: Programming Language :: Python :: 3.5
Classifier: Programming Language :: Python :: 3.6
Classifier: Programming Language :: Python :: 3.7
Classifier: Programming Language :: Python :: 3.8
